asyncio_event_loop_monitor/__init__.py
asyncio_event_loop_monitor/monitor.py
asyncio_event_loop_monitor/py.typed
asyncio_event_loop_monitor-0.1.0.dist-info/METADATA
asyncio_event_loop_monitor-0.1.0.dist-info/WHEEL
asyncio_event_loop_monitor-0.1.0.dist-info/licenses/LICENSE
asyncio_event_loop_monitor-0.1.0.dist-info/RECORD
