Metadata-Version: 2.4
Name: asyncio-event-loop-monitor
Version: 0.1.0
Summary: Detect and monitor synchronous blocking calls in Python asyncio event loops
Project-URL: Homepage, https://github.com/thehellmaker/asyncio-event-loop-monitor
Project-URL: Documentation, https://github.com/thehellmaker/asyncio-event-loop-monitor#readme
Project-URL: Repository, https://github.com/thehellmaker/asyncio-event-loop-monitor
Project-URL: Issues, https://github.com/thehellmaker/asyncio-event-loop-monitor/issues
Author-email: Akash Ashok <akash.ashok@gmail.com>
Maintainer-email: Akash Ashok <akash.ashok@gmail.com>
License: Apache-2.0
License-File: LICENSE
Keywords: async,asyncio,blocking,debugging,event-loop,monitoring,performance,profiling
Classifier: Development Status :: 4 - Beta
Classifier: Framework :: AsyncIO
Classifier: Intended Audience :: Developers
Classifier: License :: OSI Approved :: Apache Software License
Classifier: Operating System :: OS Independent
Classifier: Programming Language :: Python :: 3
Classifier: Programming Language :: Python :: 3.10
Classifier: Programming Language :: Python :: 3.11
Classifier: Programming Language :: Python :: 3.12
Classifier: Programming Language :: Python :: 3.13
Classifier: Topic :: Software Development :: Debuggers
Classifier: Topic :: Software Development :: Libraries :: Python Modules
Classifier: Topic :: System :: Monitoring
Classifier: Typing :: Typed
Requires-Python: >=3.10
Provides-Extra: dev
Requires-Dist: mypy>=1.13.0; extra == 'dev'
Requires-Dist: pytest-asyncio>=0.24.0; extra == 'dev'
Requires-Dist: pytest>=8.0.0; extra == 'dev'
Requires-Dist: ruff>=0.8.0; extra == 'dev'
